polymarket_us/__init__.py
polymarket_us/async_client.py
polymarket_us/auth.py
polymarket_us/client.py
polymarket_us/errors.py
polymarket_us/py.typed
polymarket_us/resource.py
polymarket_us/resources/__init__.py
polymarket_us/resources/account.py
polymarket_us/resources/events.py
polymarket_us/resources/markets.py
polymarket_us/resources/orders.py
polymarket_us/resources/portfolio.py
polymarket_us/resources/search.py
polymarket_us/resources/series.py
polymarket_us/resources/sports.py
polymarket_us/types/__init__.py
polymarket_us/types/account.py
polymarket_us/types/common.py
polymarket_us/types/events.py
polymarket_us/types/markets.py
polymarket_us/types/orders.py
polymarket_us/types/portfolio.py
polymarket_us/types/search.py
polymarket_us/types/series.py
polymarket_us/types/sports.py
polymarket_us/websocket/__init__.py
polymarket_us/websocket/base.py
polymarket_us/websocket/markets.py
polymarket_us/websocket/private.py
polymarket_us/websocket/types.py
polymarket_us-0.1.1.dist-info/METADATA
polymarket_us-0.1.1.dist-info/WHEEL
polymarket_us-0.1.1.dist-info/licenses/LICENSE
polymarket_us-0.1.1.dist-info/RECORD
