Metadata-Version: 2.4
Name: polymarket-us
Version: 0.1.1
Summary: Polymarket US Python SDK
Project-URL: Homepage, https://docs.polymarket.us
Project-URL: Repository, https://github.com/Polymarket/polymarket-us-python
Project-URL: Documentation, https://docs.polymarket.us
Author: Polymarket Team
License-Expression: MIT
License-File: LICENSE
Keywords: api,polymarket,prediction-markets,sdk,trading
Classifier: Development Status :: 4 - Beta
Classifier: Intended Audience :: Developers
Classifier: License :: OSI Approved :: MIT License
Classifier: Operating System :: OS Independent
Classifier: Programming Language :: Python :: 3
Classifier: Programming Language :: Python :: 3.10
Classifier: Programming Language :: Python :: 3.11
Classifier: Programming Language :: Python :: 3.12
Classifier: Programming Language :: Python :: 3.13
Classifier: Topic :: Software Development :: Libraries :: Python Modules
Classifier: Typing :: Typed
Requires-Python: >=3.10
Requires-Dist: httpx>=0.27.0
Requires-Dist: pynacl>=1.5.0
Requires-Dist: websockets>=12.0
Provides-Extra: dev
Requires-Dist: mypy>=1.10.0; extra == 'dev'
Requires-Dist: pytest-asyncio>=0.23.0; extra == 'dev'
Requires-Dist: pytest-httpx>=0.30.0; extra == 'dev'
Requires-Dist: pytest>=8.0.0; extra == 'dev'
Requires-Dist: ruff>=0.4.0; extra == 'dev'
